{
  "dialect": "postgresql",
  "entries": [
    {
      "breakpoints": true,
      "idx": 0,
      "tag": "0000_omniscient_rocket_raccoon",
      "version": "7",
      "when": 1759511580580
    },
    {
      "breakpoints": true,
      "idx": 1,
      "tag": "0001_giant_alex_power",
      "version": "7",
      "when": 1759511800793
    },
    {
      "breakpoints": true,
      "idx": 2,
      "tag": "0002_abnormal_rictor",
      "version": "7",
      "when": 1759511824731
    },
    {
      "breakpoints": true,
      "idx": 3,
      "tag": "0003_fantastic_patch",
      "version": "7",
      "when": 1759511844563
    },
    {
      "breakpoints": true,
      "idx": 4,
      "tag": "0004_remarkable_eternity",
      "version": "7",
      "when": 1759530970261
    }
  ],
  "version": "7"
}
